README.md
setup.py
repo2charliecloud/__init__.py
repo2charliecloud.egg-info/PKG-INFO
repo2charliecloud.egg-info/SOURCES.txt
repo2charliecloud.egg-info/dependency_links.txt
repo2charliecloud.egg-info/entry_points.txt
repo2charliecloud.egg-info/requires.txt
repo2charliecloud.egg-info/top_level.txt