Metadata-Version: 1.0
Name: repo2charliecloud
Version: 0.0.2
Summary: JupyterHub Spawner for Kubernetes
Home-page: UNKNOWN
Author: Yuvi Panda
Author-email: yuvipanda@gmail.com
License: BSD
Platform: UNKNOWN
